{
  "id": "assets-folder",
  "title": "14 - Assets folder",
  "description": "Brakeza3D expects to find each type of resource in its corresponding root folder. Inside the assets",
  "source": "@site/docs/14-assets-folder.md",
  "sourceDirName": ".",
  "slug": "/assets-folder",
  "permalink": "/brakeza3d/docs/assets-folder",
  "draft": false,
  "unlisted": false,
  "tags": [],
  "version": "current",
  "sidebarPosition": 15,
  "frontMatter": {
    "sidebar_position": 15
  },
  "sidebar": "tutorialSidebar",
  "previous": {
    "title": "13 - Components",
    "permalink": "/brakeza3d/docs/components"
  },
  "next": {
    "title": "Building from source",
    "permalink": "/brakeza3d/docs/building-from-source"
  }
}