{
  "name": "26",
  "scene": "scene26.json",
  "music": "musicLevels06",
  "backgroundImage": "levels/bg_06.png",
  "foregroundImage": "foregrounds/03.png",
  "allowEnergyShield": true,
  "histories": [],
  "color": { "r": 0, "g": 255, "b": 0 },
  "endLevel": false,
  "enemies": [
    {
      "name": "Colossus",
      "avatar": "avatars/14.png",
      "avatarHud": "avatars/14.png",
      "position": { "x": 85, "y": 85 },
      "model": "spaceships/Zenith.fbx",
      "size": { "x": 1, "y": 1,  "z": 1 },
      "enableLights": true,
      "animated": true,
      "stamina": 1000,
      "reward": true,
      "motion": {
        "type": "none"
      },
      "weapon": {
        "index": 0,
        "available": true,
        "name": "Linear",
        "damage": 10,
        "amount": 999,
        "startAmount": 1000,
        "speed": 1,
        "dispersion": 10,
        "accuracy": 50,
        "cadenceTime": 0.20,
        "stop": true,
        "stopDuration": 3,
        "stopEvery": 5,
        "type": "laser",
        "icon": "icons/weapon_projectile.png",
        "modelProjectile": "projectile_weapon_01_magenta.fbx",
        "model": "item_weapon_01.fbx",
        "flatTexture": true,
        "enableLights": false,
        "color": { "r": 255, "g": 0, "b": 0 }
      },
      "emitter": []
    },{
      "name": "Colossus",
      "avatar": "avatars/14.png",
      "avatarHud": "avatars/14.png",
      "position": { "x": 15, "y": 85 },
      "model": "spaceships/Zenith.fbx",
      "size": { "x": 1, "y": 1,  "z": 1 },
      "enableLights": true,
      "animated": true,
      "stamina": 1000,
      "reward": true,
      "motion": {
        "type": "none"
      },
      "weapon": {
        "index": 0,
        "available": true,
        "name": "Linear",
        "damage": 10,
        "amount": 999,
        "startAmount": 1000,
        "speed": 1,
        "dispersion": 10,
        "accuracy": 50,
        "cadenceTime": 0.20,
        "stop": true,
        "stopDuration": 3,
        "stopEvery": 5,
        "type": "laser",
        "icon": "icons/weapon_projectile.png",
        "modelProjectile": "projectile_weapon_01_magenta.fbx",
        "model": "item_weapon_01.fbx",
        "flatTexture": true,
        "enableLights": false,
        "color": { "r": 255, "g": 0, "b": 0 }
      },
      "emitter": []
    },
    {
      "name": "Bomb01",
      "avatar": "avatars/energy_ball.png",
      "avatarHud": "avatars/14.png",
      "size": { "x": 1, "y": 1,  "z": 1 },
      "position": { "x": 50,  "y": 45 },
      "model": "bomb02.fbx",
      "enableLights": true,
      "animated": true,
      "stamina": 600,
      "reward": true,
      "motion": {
        "type": "path",
        "speed": 0.25,
        "points": [
          { "x": 10, "y": 10 },
          { "x": 10, "y": 40 },
          { "x": 10, "y": 10 }
        ]
      },
      "explode": 100,
      "weapon": {
        "index": 0,
        "available": false,
        "name": "Linear",
        "damage": 15,
        "amount": 999,
        "startAmount": 100,
        "speed": 1,
        "dispersion": 10,
        "accuracy": 100,
        "cadenceTime": 1.0,
        "stop": false,
        "stopDuration": 2,
        "stopEvery": 6,
        "type": "laser",
        "icon": "icons/weapon_projectile.png",
        "modelProjectile": "projectile_weapon_01_magenta.fbx",
        "model": "item_weapon_02.fbx",
        "flatTexture": true,
        "enableLights": false,
        "color": { "r": 255, "g": 255, "b": 0 }
      }
    },
    {
      "name": "Bomb02",
      "avatar": "avatars/energy_ball.png",
      "avatarHud": "avatars/14.png",
      "size": { "x": 1, "y": 1,  "z": 1 },
      "position": { "x": 50,  "y": 45 },
      "model": "bomb02.fbx",
      "enableLights": true,
      "animated": true,
      "stamina": 600,
      "reward": true,
      "motion": {
        "type": "path",
        "speed": 0.25,
        "points": [
          { "x": 90, "y": 10 },
          { "x": 90, "y": 40 },
          { "x": 90, "y": 10 }
        ]
      },
      "explode": 100,
      "weapon": {
        "index": 0,
        "available": false,
        "name": "Linear",
        "damage": 15,
        "amount": 999,
        "startAmount": 100,
        "speed": 1,
        "dispersion": 10,
        "accuracy": 100,
        "cadenceTime": 1.0,
        "stop": false,
        "stopDuration": 2,
        "stopEvery": 6,
        "type": "laser",
        "icon": "icons/weapon_projectile.png",
        "modelProjectile": "projectile_weapon_01_magenta.fbx",
        "model": "item_weapon_02.fbx",
        "flatTexture": true,
        "enableLights": false,
        "color": { "r": 255, "g": 255, "b": 0 }
      }
    },
    {
      "name": "RedBallLaser01",
      "avatar": "avatars/energy_ball.png",
      "avatarHud": "avatars/14.png",
      "position": { "x": 50,  "y": 10 },
      "model": "energy_ball.fbx",
      "size": { "x": 1, "y": 1,  "z": 1 },
      "enableLights": true,
      "animated": true,
      "stamina": 600,
      "reward": true,
      "motion": {
        "type": "path",
        "speed": 0.4,
        "points": [
          { "x": 70, "y": 40 },
          { "x": 70, "y": 60 },
          { "x": 50, "y": 60 },
          { "x": 30, "y": 60 },
          { "x": 30, "y": 40 },
          { "x": 30, "y": 30 },
          { "x": 50, "y": 30 },
          { "x": 70, "y": 30 },
          { "x": 70, "y": 40 }
        ]
      },
      "weapon": {
        "index": 0,
        "available": false,
        "name": "Linear",
        "damage": 20,
        "amount": 999,
        "startAmount": 100,
        "speed": 1,
        "dispersion": 10,
        "accuracy": 100,
        "cadenceTime": 1.0,
        "stop": false,
        "stopDuration": 2,
        "stopEvery": 6,
        "type": "laser",
        "icon": "icons/weapon_projectile.png",
        "modelProjectile": "projectile_weapon_01_magenta.fbx",
        "model": "item_weapon_02.fbx",
        "flatTexture": true,
        "enableLights": false,
        "color": { "r": 255, "g": 255, "b": 0 }
      }
    },
    {
      "name": "RedBallLaser02",
      "avatar": "avatars/energy_ball.png",
      "avatarHud": "avatars/14.png",
      "position": { "x": 50,  "y": 10 },
      "model": "energy_ball.fbx",
      "size": { "x": 1, "y": 1,  "z": 1 },
      "enableLights": true,
      "animated": true,
      "stamina": 600,
      "reward": true,
      "motion": {
        "type": "path",
        "speed": 0.4,
        "points": [
          { "x": 30, "y": 40 },
          { "x": 30, "y": 30 },
          { "x": 50, "y": 30 },
          { "x": 70, "y": 30 },
          { "x": 70, "y": 40 },
          { "x": 70, "y": 60 },
          { "x": 50, "y": 60 },
          { "x": 30, "y": 60 },
          { "x": 30, "y": 40 }
        ]
      },
      "weapon": {
        "index": 0,
        "available": false,
        "name": "Linear",
        "damage": 20,
        "amount": 999,
        "startAmount": 100,
        "speed": 1,
        "dispersion": 10,
        "accuracy": 100,
        "cadenceTime": 1.0,
        "stop": false,
        "stopDuration": 2,
        "stopEvery": 6,
        "type": "laser",
        "icon": "icons/weapon_projectile.png",
        "modelProjectile": "projectile_weapon_01_magenta.fbx",
        "model": "item_weapon_02.fbx",
        "flatTexture": true,
        "enableLights": false,
        "color": { "r": 255, "g": 255, "b": 0 }
      }
    }
  ],
  "lasers": [{
    "targetOne": "RedBallLaser01",
    "targetTwo": "RedBallLaser02",
    "color": { "r": 255, "g": 0, "b": 0 }
  }],
  "items": [
  ]
}